Workbook

Sheet Inicio
A1: Presupuesto Familiar 2027 con IPC
A2: Un presupuesto anual en pesos que se ajusta solo por la inflación que cargues. Excel y Google Sheets.
A4: CÓMO USARLO
A5: 1. Pestaña 'Parámetros': cargá el IPC esperado para cada mes de 2027 (por ejemplo 2,5%) y tus ingresos de enero con el aumento mensual que esperás.
A6: 2. Pestaña 'Presupuesto': en cada rubro poné el gasto base de enero y si ajusta por IPC (SI/NO). Los meses siguientes se calculan solos.
A7: 3. Pestaña 'Real': cargá lo que gastaste de verdad cada mes. Compará contra el presupuesto.
A8: 4. Pestaña 'Resumen': ingresos, gastos, ahorro, ahorro acumulado y si tus ingresos le ganan a la inflación (poder de compra).
A9: 5. Cuando el INDEC publique el IPC real de cada mes, reemplazá el esperado por el real y todo se recalcula (fuente: indec.gob.ar).
A11: Celdas amarillas = las cargás vos. Celdas celestes = se calculan solas. Los números de ejemplo son referencia: pisalos con los tuyos.
A13: AVISO
A14: Herramienta de cálculo orientativa. No es asesoramiento financiero. Los valores de ejemplo no son predicciones. Para uso propio, prohibida su reventa.

Sheet Parámetros
A1: Parámetros
A2: IPC mensual esperado e ingresos
A4: Concepto | B4: Ene | C4: Feb | D4: Mar | E4: Abr | F4: May | G4: Jun | H4: Jul | I4: Ago | J4: Sep | K4: Oct | L4: Nov | M4: Dic
A5: IPC mensual esperado | B5: 0.025 | C5: 0.025 | D5: 0.025 | E5: 0.025 | F5: 0.025 | G5: 0.025 | H5: 0.025 | I5: 0.025 | J5: 0.025 | K5: 0.025 | L5: 0.025 | M5: 0.025
A6: Índice de precios (enero = 1) | B6: 1 | C6: =B6*(1+C5) | D6: =C6*(1+D5) | E6: =D6*(1+E5) | F6: =E6*(1+F5) | G6: =F6*(1+G5) | H6: =G6*(1+H5) | I6: =H6*(1+I5) | J6: =I6*(1+J5) | ... M6: =L6*(1+M5)
A8: Ingresos de enero | B8: 1500000
A9: Aumento mensual esperado de ingresos | B9: 0.02
A10: Meta de ahorro mensual (% del ingreso) | B10: 0.1

Sheet Presupuesto
A1: Presupuesto 2027
A2: Gasto base de enero y ajuste mensual por IPC
A4: Rubro | B4: Base enero | C4: Ajusta IPC | D4: Ene | E4: Feb | F4: Mar | G4: Abr | H4: May | I4: Jun | J4: Jul | K4: Ago | L4: Sep | M4: Oct | N4: Nov | O4: Dic | P4: Total año
A5: Alquiler / cuota de vivienda | B5: 450000 | C5: SI | D5: =$B5*IF($C5="SI",Parámetros!B$6,1) | E5: =$B5*IF($C5="SI",Parámetros!C$6,1) | F5: =$B5*IF($C5="SI",Parámetros!D$6,1) | G5: =$B5*IF($C5="SI",Parámetros!E$6,1) | H5: =$B5*IF($C5="SI",Parámetros!F$6,1) | I5: =$B5*IF($C5="SI",Parámetros!G$6,1) | J5: =$B5*IF($C5="SI",Parámetros!H$6,1) | K5: =$B5*IF($C5="SI",Parámetros!I$6,1) | ... O5: =$B5*IF($C5="SI",Parámetros!M$6,1) | P5: =SUM(D5:O5)
A6: Expensas y servicios | B6: 120000 | C6: SI | D6: =$B6*IF($C6="SI",Parámetros!B$6,1) | E6: =$B6*IF($C6="SI",Parámetros!C$6,1) | F6: =$B6*IF($C6="SI",Parámetros!D$6,1) | G6: =$B6*IF($C6="SI",Parámetros!E$6,1) | H6: =$B6*IF($C6="SI",Parámetros!F$6,1) | I6: =$B6*IF($C6="SI",Parámetros!G$6,1) | J6: =$B6*IF($C6="SI",Parámetros!H$6,1) | K6: =$B6*IF($C6="SI",Parámetros!I$6,1) | ... O6: =$B6*IF($C6="SI",Parámetros!M$6,1) | P6: =SUM(D6:O6)
A7: Supermercado | B7: 350000 | C7: SI | D7: =$B7*IF($C7="SI",Parámetros!B$6,1) | E7: =$B7*IF($C7="SI",Parámetros!C$6,1) | F7: =$B7*IF($C7="SI",Parámetros!D$6,1) | G7: =$B7*IF($C7="SI",Parámetros!E$6,1) | H7: =$B7*IF($C7="SI",Parámetros!F$6,1) | I7: =$B7*IF($C7="SI",Parámetros!G$6,1) | J7: =$B7*IF($C7="SI",Parámetros!H$6,1) | K7: =$B7*IF($C7="SI",Parámetros!I$6,1) | ... O7: =$B7*IF($C7="SI",Parámetros!M$6,1) | P7: =SUM(D7:O7)
A8: Transporte | B8: 80000 | C8: SI | D8: =$B8*IF($C8="SI",Parámetros!B$6,1) | E8: =$B8*IF($C8="SI",Parámetros!C$6,1) | F8: =$B8*IF($C8="SI",Parámetros!D$6,1) | G8: =$B8*IF($C8="SI",Parámetros!E$6,1) | H8: =$B8*IF($C8="SI",Parámetros!F$6,1) | I8: =$B8*IF($C8="SI",Parámetros!G$6,1) | J8: =$B8*IF($C8="SI",Parámetros!H$6,1) | K8: =$B8*IF($C8="SI",Parámetros!I$6,1) | ... O8: =$B8*IF($C8="SI",Parámetros!M$6,1) | P8: =SUM(D8:O8)
A9: Salud y prepaga | B9: 150000 | C9: SI | D9: =$B9*IF($C9="SI",Parámetros!B$6,1) | E9: =$B9*IF($C9="SI",Parámetros!C$6,1) | F9: =$B9*IF($C9="SI",Parámetros!D$6,1) | G9: =$B9*IF($C9="SI",Parámetros!E$6,1) | H9: =$B9*IF($C9="SI",Parámetros!F$6,1) | I9: =$B9*IF($C9="SI",Parámetros!G$6,1) | J9: =$B9*IF($C9="SI",Parámetros!H$6,1) | K9: =$B9*IF($C9="SI",Parámetros!I$6,1) | ... O9: =$B9*IF($C9="SI",Parámetros!M$6,1) | P9: =SUM(D9:O9)
A10: Educación | B10: 100000 | C10: SI | D10: =$B10*IF($C10="SI",Parámetros!B$6,1) | E10: =$B10*IF($C10="SI",Parámetros!C$6,1) | F10: =$B10*IF($C10="SI",Parámetros!D$6,1) | G10: =$B10*IF($C10="SI",Parámetros!E$6,1) | H10: =$B10*IF($C10="SI",Parámetros!F$6,1) | I10: =$B10*IF($C10="SI",Parámetros!G$6,1) | J10: =$B10*IF($C10="SI",Parámetros!H$6,1) | K10: =$B10*IF($C10="SI",Parámetros!I$6,1) | ... O10: =$B10*IF($C10="SI",Parámetros!M$6,1) | P10: =SUM(D10:O10)
A11: Ocio y salidas | B11: 80000 | C11: NO | D11: =$B11*IF($C11="SI",Parámetros!B$6,1) | E11: =$B11*IF($C11="SI",Parámetros!C$6,1) | F11: =$B11*IF($C11="SI",Parámetros!D$6,1) | G11: =$B11*IF($C11="SI",Parámetros!E$6,1) | H11: =$B11*IF($C11="SI",Parámetros!F$6,1) | I11: =$B11*IF($C11="SI",Parámetros!G$6,1) | J11: =$B11*IF($C11="SI",Parámetros!H$6,1) | K11: =$B11*IF($C11="SI",Parámetros!I$6,1) | ... O11: =$B11*IF($C11="SI",Parámetros!M$6,1) | P11: =SUM(D11:O11)
A12: Seguros e impuestos | B12: 40000 | C12: SI | D12: =$B12*IF($C12="SI",Parámetros!B$6,1) | E12: =$B12*IF($C12="SI",Parámetros!C$6,1) | F12: =$B12*IF($C12="SI",Parámetros!D$6,1) | G12: =$B12*IF($C12="SI",Parámetros!E$6,1) | H12: =$B12*IF($C12="SI",Parámetros!F$6,1) | I12: =$B12*IF($C12="SI",Parámetros!G$6,1) | J12: =$B12*IF($C12="SI",Parámetros!H$6,1) | K12: =$B12*IF($C12="SI",Parámetros!I$6,1) | ... O12: =$B12*IF($C12="SI",Parámetros!M$6,1) | P12: =SUM(D12:O12)
A13: Deudas y cuotas | B13: 60000 | C13: NO | D13: =$B13*IF($C13="SI",Parámetros!B$6,1) | E13: =$B13*IF($C13="SI",Parámetros!C$6,1) | F13: =$B13*IF($C13="SI",Parámetros!D$6,1) | G13: =$B13*IF($C13="SI",Parámetros!E$6,1) | H13: =$B13*IF($C13="SI",Parámetros!F$6,1) | I13: =$B13*IF($C13="SI",Parámetros!G$6,1) | J13: =$B13*IF($C13="SI",Parámetros!H$6,1) | K13: =$B13*IF($C13="SI",Parámetros!I$6,1) | ... O13: =$B13*IF($C13="SI",Parámetros!M$6,1) | P13: =SUM(D13:O13)
A14: Otros | B14: 30000 | C14: NO | D14: =$B14*IF($C14="SI",Parámetros!B$6,1) | E14: =$B14*IF($C14="SI",Parámetros!C$6,1) | F14: =$B14*IF($C14="SI",Parámetros!D$6,1) | G14: =$B14*IF($C14="SI",Parámetros!E$6,1) | H14: =$B14*IF($C14="SI",Parámetros!F$6,1) | I14: =$B14*IF($C14="SI",Parámetros!G$6,1) | J14: =$B14*IF($C14="SI",Parámetros!H$6,1) | K14: =$B14*IF($C14="SI",Parámetros!I$6,1) | ... O14: =$B14*IF($C14="SI",Parámetros!M$6,1) | P14: =SUM(D14:O14)
A15: TOTAL | D15: =SUM(D5:D14) | E15: =SUM(E5:E14) | F15: =SUM(F5:F14) | G15: =SUM(G5:G14) | H15: =SUM(H5:H14) | I15: =SUM(I5:I14) | J15: =SUM(J5:J14) | K15: =SUM(K5:K14) | ... P15: =SUM(P5:P14)

Sheet Real
A1: Gasto real 2027
A2: Cargá lo que gastaste cada mes
A4: Rubro | D4: Ene | E4: Feb | F4: Mar | G4: Abr | H4: May | I4: Jun | J4: Jul | K4: Ago | L4: Sep | M4: Oct | N4: Nov | O4: Dic | P4: Total año
A5: Alquiler / cuota de vivienda | D5: 0 | E5: 0 | F5: 0 | G5: 0 | H5: 0 | I5: 0 | J5: 0 | K5: 0 | L5: 0 | M5: 0 | N5: 0 | O5: 0 | P5: =SUM(D5:O5)
A6: Expensas y servicios | D6: 0 | E6: 0 | F6: 0 | G6: 0 | H6: 0 | I6: 0 | J6: 0 | K6: 0 | L6: 0 | M6: 0 | N6: 0 | O6: 0 | P6: =SUM(D6:O6)
A7: Supermercado | D7: 0 | E7: 0 | F7: 0 | G7: 0 | H7: 0 | I7: 0 | J7: 0 | K7: 0 | L7: 0 | M7: 0 | N7: 0 | O7: 0 | P7: =SUM(D7:O7)
A8: Transporte | D8: 0 | E8: 0 | F8: 0 | G8: 0 | H8: 0 | I8: 0 | J8: 0 | K8: 0 | L8: 0 | M8: 0 | N8: 0 | O8: 0 | P8: =SUM(D8:O8)
A9: Salud y prepaga | D9: 0 | E9: 0 | F9: 0 | G9: 0 | H9: 0 | I9: 0 | J9: 0 | K9: 0 | L9: 0 | M9: 0 | N9: 0 | O9: 0 | P9: =SUM(D9:O9)
A10: Educación | D10: 0 | E10: 0 | F10: 0 | G10: 0 | H10: 0 | I10: 0 | J10: 0 | K10: 0 | L10: 0 | M10: 0 | N10: 0 | O10: 0 | P10: =SUM(D10:O10)
A11: Ocio y salidas | D11: 0 | E11: 0 | F11: 0 | G11: 0 | H11: 0 | I11: 0 | J11: 0 | K11: 0 | L11: 0 | M11: 0 | N11: 0 | O11: 0 | P11: =SUM(D11:O11)
A12: Seguros e impuestos | D12: 0 | E12: 0 | F12: 0 | G12: 0 | H12: 0 | I12: 0 | J12: 0 | K12: 0 | L12: 0 | M12: 0 | N12: 0 | O12: 0 | P12: =SUM(D12:O12)
A13: Deudas y cuotas | D13: 0 | E13: 0 | F13: 0 | G13: 0 | H13: 0 | I13: 0 | J13: 0 | K13: 0 | L13: 0 | M13: 0 | N13: 0 | O13: 0 | P13: =SUM(D13:O13)
A14: Otros | D14: 0 | E14: 0 | F14: 0 | G14: 0 | H14: 0 | I14: 0 | J14: 0 | K14: 0 | L14: 0 | M14: 0 | N14: 0 | O14: 0 | P14: =SUM(D14:O14)
A15: TOTAL | D15: =SUM(D5:D14) | E15: =SUM(E5:E14) | F15: =SUM(F5:F14) | G15: =SUM(G5:G14) | H15: =SUM(H5:H14) | I15: =SUM(I5:I14) | J15: =SUM(J5:J14) | K15: =SUM(K5:K14) | ... P15: =SUM(P5:P14)

Sheet Resumen
A1: Resumen del año
A2: Ingresos, gastos, ahorro y poder de compra
A4: Concepto | D4: Ene | E4: Feb | F4: Mar | G4: Abr | H4: May | I4: Jun | J4: Jul | K4: Ago | L4: Sep | M4: Oct | N4: Nov | O4: Dic | P4: Total año
A5: Ingresos | D5: =Parámetros!$B$8*(1+Parámetros!$B$9)^0 | E5: =Parámetros!$B$8*(1+Parámetros!$B$9)^1 | F5: =Parámetros!$B$8*(1+Parámetros!$B$9)^2 | G5: =Parámetros!$B$8*(1+Parámetros!$B$9)^3 | H5: =Parámetros!$B$8*(1+Parámetros!$B$9)^4 | I5: =Parámetros!$B$8*(1+Parámetros!$B$9)^5 | J5: =Parámetros!$B$8*(1+Parámetros!$B$9)^6 | K5: =Parámetros!$B$8*(1+Parámetros!$B$9)^7 | L5: =Parámetros!$B$8*(1+Parámetros!$B$9)^8 | M5: =Parámetros!$B$8*(1+Parámetros!$B$9)^9 | N5: =Parámetros!$B$8*(1+Parámetros!$B$9)^10 | O5: =Parámetros!$B$8*(1+Parámetros!$B$9)^11 | P5: =SUM(D5:O5)
A6: Gasto presupuestado | D6: =Presupuesto!D15 | E6: =Presupuesto!E15 | F6: =Presupuesto!F15 | G6: =Presupuesto!G15 | H6: =Presupuesto!H15 | I6: =Presupuesto!I15 | J6: =Presupuesto!J15 | K6: =Presupuesto!K15 | ... O6: =Presupuesto!O15 | P6: =SUM(D6:O6)
A7: Ahorro presupuestado | D7: =D5-D6 | E7: =E5-E6 | F7: =F5-F6 | G7: =G5-G6 | H7: =H5-H6 | I7: =I5-I6 | J7: =J5-J6 | K7: =K5-K6 | ... O7: =O5-O6 | P7: =SUM(D7:O7)
A8: Meta de ahorro | D8: =D5*Parámetros!$B$10 | E8: =E5*Parámetros!$B$10 | F8: =F5*Parámetros!$B$10 | G8: =G5*Parámetros!$B$10 | H8: =H5*Parámetros!$B$10 | I8: =I5*Parámetros!$B$10 | J8: =J5*Parámetros!$B$10 | K8: =K5*Parámetros!$B$10 | ... O8: =O5*Parámetros!$B$10 | P8: =SUM(D8:O8)
A9: Ahorro acumulado | D9: =SUM($D7:D7) | E9: =SUM($D7:E7) | F9: =SUM($D7:F7) | G9: =SUM($D7:G7) | H9: =SUM($D7:H7) | I9: =SUM($D7:I7) | J9: =SUM($D7:J7) | K9: =SUM($D7:K7) | ... O9: =SUM($D7:O7)
A10: Gasto real | D10: =Real!D15 | E10: =Real!E15 | F10: =Real!F15 | G10: =Real!G15 | H10: =Real!H15 | I10: =Real!I15 | J10: =Real!J15 | K10: =Real!K15 | ... O10: =Real!O15 | P10: =SUM(D10:O10)
A11: Diferencia (presupuesto - real) | D11: =D6-D10 | E11: =E6-E10 | F11: =F6-F10 | G11: =G6-G10 | H11: =H6-H10 | I11: =I6-I10 | J11: =J6-J10 | K11: =K6-K10 | ... O11: =O6-O10 | P11: =SUM(D11:O11)
A12: Ingreso real (a precios de enero) | D12: =D5/Parámetros!B6 | E12: =E5/Parámetros!C6 | F12: =F5/Parámetros!D6 | G12: =G5/Parámetros!E6 | H12: =H5/Parámetros!F6 | I12: =I5/Parámetros!G6 | J12: =J5/Parámetros!H6 | K12: =K5/Parámetros!I6 | ... O12: =O5/Parámetros!M6
A14: Si 'Ingreso real' baja mes a mes, tus ingresos no le ganan a la inflación esperada.
