Workbook

Sheet Inicio
A1: Stock, costos y ventas para la temporada
A2: Para saber cuánto ganás de verdad, qué reponer y cuánta plata tenés parada en mercadería. Excel y Google Sheets.
A4: CÓMO USARLA
A5: 1. Pestaña 'Parámetros': cargá tus costos fijos del período (puesto, internet, cuota de monotributo, packaging) y tu meta de ganancia.
A6: 2. Pestaña 'Productos': una fila por producto con lo que te cuesta, a cuánto lo vendés, el % de comisión y envío, el stock que compraste y tu stock mínimo. El margen se calcula solo.
A7: 3. Pestaña 'Ventas': una fila por venta (fecha, producto, cantidad). Elegí el producto de la lista. Si vendiste a otro precio, escribilo en 'Precio real'.
A8: 4. De vuelta en 'Productos' ves cuántas unidades vendiste, cuánto stock te queda y el aviso REPONER cuando llegás al mínimo.
A9: 5. Pestaña 'Resumen': ingresos, costo de la mercadería vendida, comisiones, ganancia neta, plata parada en stock y producto más rentable.
A11: Celdas amarillas = las cargás vos. Celdas celestes = se calculan solas. Los productos de ejemplo son referencia: pisalos con los tuyos (hasta 40 productos y 500 ventas).
A12: El % de comisión y envío lo calculás vos como porcentaje del precio (por ejemplo: la comisión de la plataforma de cobro o de la tienda online, más lo que absorbés de envío).
A14: AVISO
A15: Herramienta de cálculo orientativa. No es asesoramiento contable ni impositivo. No incluye impuestos: consultá con tu contador. Para uso propio, prohibida su reventa.

Sheet Parámetros
A1: Parámetros
A2: Costos fijos del período y meta
A4: Costos fijos del período (puesto, internet, monotributo, packaging) | B4: 150000
A5: Meta de ganancia neta del período | B5: 400000
A7: Los costos fijos se pagan venda lo que venda. El Resumen los descuenta de la ganancia bruta.

Sheet Productos
A1: Productos y stock
A2: Costo, precio, stock inicial y mínimo; el resto se calcula
A4: Producto | B4: Costo unitario | C4: Precio de venta | D4: Comisión y envío (% del precio) | E4: Stock comprado | F4: Stock mínimo (aviso) | G4: Margen $ por unidad | H4: Margen % | I4: Unidades vendidas | J4: Stock actual | K4: Estado | L4: Ganancia del producto
A5: Vela aromática | B5: 3500 | C5: 8500 | D5: 0.05 | E5: 60 | F5: 10 | G5: =IF(A5="","",C5-B5-C5*D5) | H5: =IF(OR(A5="",C5=0),"",G5/C5) | I5: =IF(A5="","",SUMIF(Ventas!$B$5:$B$504,A5,Ventas!$C$5:$C$504)) | J5: =IF(A5="","",E5-I5) | K5: =IF(A5="","",IF(J5<=0,"SIN STOCK",IF(J5<=F5,"REPONER","OK"))) | L5: =IF(A5="","",G5*I5)
A6: Caja de alfajores x6 | B6: 4200 | C6: 9000 | D6: 0.05 | E6: 80 | F6: 15 | G6: =IF(A6="","",C6-B6-C6*D6) | H6: =IF(OR(A6="",C6=0),"",G6/C6) | I6: =IF(A6="","",SUMIF(Ventas!$B$5:$B$504,A6,Ventas!$C$5:$C$504)) | J6: =IF(A6="","",E6-I6) | K6: =IF(A6="","",IF(J6<=0,"SIN STOCK",IF(J6<=F6,"REPONER","OK"))) | L6: =IF(A6="","",G6*I6)
A7: Cuadro decorativo | B7: 6000 | C7: 15000 | D7: 0.08 | E7: 30 | F7: 5 | G7: =IF(A7="","",C7-B7-C7*D7) | H7: =IF(OR(A7="",C7=0),"",G7/C7) | I7: =IF(A7="","",SUMIF(Ventas!$B$5:$B$504,A7,Ventas!$C$5:$C$504)) | J7: =IF(A7="","",E7-I7) | K7: =IF(A7="","",IF(J7<=0,"SIN STOCK",IF(J7<=F7,"REPONER","OK"))) | L7: =IF(A7="","",G7*I7)
A8: Pulsera artesanal | B8: 1500 | C8: 4500 | D8: 0.05 | E8: 100 | F8: 20 | G8: =IF(A8="","",C8-B8-C8*D8) | H8: =IF(OR(A8="",C8=0),"",G8/C8) | I8: =IF(A8="","",SUMIF(Ventas!$B$5:$B$504,A8,Ventas!$C$5:$C$504)) | J8: =IF(A8="","",E8-I8) | K8: =IF(A8="","",IF(J8<=0,"SIN STOCK",IF(J8<=F8,"REPONER","OK"))) | L8: =IF(A8="","",G8*I8)
A9: Set de cuadernos | B9: 5200 | C9: 12000 | D9: 0.05 | E9: 40 | F9: 8 | G9: =IF(A9="","",C9-B9-C9*D9) | H9: =IF(OR(A9="",C9=0),"",G9/C9) | I9: =IF(A9="","",SUMIF(Ventas!$B$5:$B$504,A9,Ventas!$C$5:$C$504)) | J9: =IF(A9="","",E9-I9) | K9: =IF(A9="","",IF(J9<=0,"SIN STOCK",IF(J9<=F9,"REPONER","OK"))) | L9: =IF(A9="","",G9*I9)
G10: =IF(A10="","",C10-B10-C10*D10) | H10: =IF(OR(A10="",C10=0),"",G10/C10) | I10: =IF(A10="","",SUMIF(Ventas!$B$5:$B$504,A10,Ventas!$C$5:$C$504)) | J10: =IF(A10="","",E10-I10) | K10: =IF(A10="","",IF(J10<=0,"SIN STOCK",IF(J10<=F10,"REPONER","OK"))) | L10: =IF(A10="","",G10*I10)
G11: =IF(A11="","",C11-B11-C11*D11) | H11: =IF(OR(A11="",C11=0),"",G11/C11) | I11: =IF(A11="","",SUMIF(Ventas!$B$5:$B$504,A11,Ventas!$C$5:$C$504)) | J11: =IF(A11="","",E11-I11) | K11: =IF(A11="","",IF(J11<=0,"SIN STOCK",IF(J11<=F11,"REPONER","OK"))) | L11: =IF(A11="","",G11*I11)
G12: =IF(A12="","",C12-B12-C12*D12) | H12: =IF(OR(A12="",C12=0),"",G12/C12) | I12: =IF(A12="","",SUMIF(Ventas!$B$5:$B$504,A12,Ventas!$C$5:$C$504)) | J12: =IF(A12="","",E12-I12) | K12: =IF(A12="","",IF(J12<=0,"SIN STOCK",IF(J12<=F12,"REPONER","OK"))) | L12: =IF(A12="","",G12*I12)
G13: =IF(A13="","",C13-B13-C13*D13) | H13: =IF(OR(A13="",C13=0),"",G13/C13) | I13: =IF(A13="","",SUMIF(Ventas!$B$5:$B$504,A13,Ventas!$C$5:$C$504)) | J13: =IF(A13="","",E13-I13) | K13: =IF(A13="","",IF(J13<=0,"SIN STOCK",IF(J13<=F13,"REPONER","OK"))) | L13: =IF(A13="","",G13*I13)
G14: =IF(A14="","",C14-B14-C14*D14) | H14: =IF(OR(A14="",C14=0),"",G14/C14) | I14: =IF(A14="","",SUMIF(Ventas!$B$5:$B$504,A14,Ventas!$C$5:$C$504)) | J14: =IF(A14="","",E14-I14) | K14: =IF(A14="","",IF(J14<=0,"SIN STOCK",IF(J14<=F14,"REPONER","OK"))) | L14: =IF(A14="","",G14*I14)
G15: =IF(A15="","",C15-B15-C15*D15) | H15: =IF(OR(A15="",C15=0),"",G15/C15) | I15: =IF(A15="","",SUMIF(Ventas!$B$5:$B$504,A15,Ventas!$C$5:$C$504)) | J15: =IF(A15="","",E15-I15) | K15: =IF(A15="","",IF(J15<=0,"SIN STOCK",IF(J15<=F15,"REPONER","OK"))) | L15: =IF(A15="","",G15*I15)
G16: =IF(A16="","",C16-B16-C16*D16) | H16: =IF(OR(A16="",C16=0),"",G16/C16) | I16: =IF(A16="","",SUMIF(Ventas!$B$5:$B$504,A16,Ventas!$C$5:$C$504)) | J16: =IF(A16="","",E16-I16) | K16: =IF(A16="","",IF(J16<=0,"SIN STOCK",IF(J16<=F16,"REPONER","OK"))) | L16: =IF(A16="","",G16*I16)
G17: =IF(A17="","",C17-B17-C17*D17) | H17: =IF(OR(A17="",C17=0),"",G17/C17) | I17: =IF(A17="","",SUMIF(Ventas!$B$5:$B$504,A17,Ventas!$C$5:$C$504)) | J17: =IF(A17="","",E17-I17) | K17: =IF(A17="","",IF(J17<=0,"SIN STOCK",IF(J17<=F17,"REPONER","OK"))) | L17: =IF(A17="","",G17*I17)
G18: =IF(A18="","",C18-B18-C18*D18) | H18: =IF(OR(A18="",C18=0),"",G18/C18) | I18: =IF(A18="","",SUMIF(Ventas!$B$5:$B$504,A18,Ventas!$C$5:$C$504)) | J18: =IF(A18="","",E18-I18) | K18: =IF(A18="","",IF(J18<=0,"SIN STOCK",IF(J18<=F18,"REPONER","OK"))) | L18: =IF(A18="","",G18*I18)
G19: =IF(A19="","",C19-B19-C19*D19) | H19: =IF(OR(A19="",C19=0),"",G19/C19) | I19: =IF(A19="","",SUMIF(Ventas!$B$5:$B$504,A19,Ventas!$C$5:$C$504)) | J19: =IF(A19="","",E19-I19) | K19: =IF(A19="","",IF(J19<=0,"SIN STOCK",IF(J19<=F19,"REPONER","OK"))) | L19: =IF(A19="","",G19*I19)
G20: =IF(A20="","",C20-B20-C20*D20) | H20: =IF(OR(A20="",C20=0),"",G20/C20) | I20: =IF(A20="","",SUMIF(Ventas!$B$5:$B$504,A20,Ventas!$C$5:$C$504)) | J20: =IF(A20="","",E20-I20) | K20: =IF(A20="","",IF(J20<=0,"SIN STOCK",IF(J20<=F20,"REPONER","OK"))) | L20: =IF(A20="","",G20*I20)
G21: =IF(A21="","",C21-B21-C21*D21) | H21: =IF(OR(A21="",C21=0),"",G21/C21) | I21: =IF(A21="","",SUMIF(Ventas!$B$5:$B$504,A21,Ventas!$C$5:$C$504)) | J21: =IF(A21="","",E21-I21) | K21: =IF(A21="","",IF(J21<=0,"SIN STOCK",IF(J21<=F21,"REPONER","OK"))) | L21: =IF(A21="","",G21*I21)
... G44: =IF(A44="","",C44-B44-C44*D44) | H44: =IF(OR(A44="",C44=0),"",G44/C44) | I44: =IF(A44="","",SUMIF(Ventas!$B$5:$B$504,A44,Ventas!$C$5:$C$504)) | J44: =IF(A44="","",E44-I44) | K44: =IF(A44="","",IF(J44<=0,"SIN STOCK",IF(J44<=F44,"REPONER","OK"))) | L44: =IF(A44="","",G44*I44)

Sheet Ventas
A1: Ventas
A2: Una fila por venta. Elegí el producto de la lista
A4: Fecha | B4: Producto | C4: Cantidad | D4: Precio real (opcional) | E4: Importe
A5: 46357 | B5: Vela aromática | C5: 3 | E5: =IF(B5="","",C5*IF(D5>0,D5,IFERROR(VLOOKUP(B5,Productos!$A$5:$C$44,3,FALSE),0)))
A6: 46358 | B6: Caja de alfajores x6 | C6: 5 | E6: =IF(B6="","",C6*IF(D6>0,D6,IFERROR(VLOOKUP(B6,Productos!$A$5:$C$44,3,FALSE),0)))
A7: 46359 | B7: Pulsera artesanal | C7: 8 | E7: =IF(B7="","",C7*IF(D7>0,D7,IFERROR(VLOOKUP(B7,Productos!$A$5:$C$44,3,FALSE),0)))
A8: 46361 | B8: Cuadro decorativo | C8: 1 | E8: =IF(B8="","",C8*IF(D8>0,D8,IFERROR(VLOOKUP(B8,Productos!$A$5:$C$44,3,FALSE),0)))
E9: =IF(B9="","",C9*IF(D9>0,D9,IFERROR(VLOOKUP(B9,Productos!$A$5:$C$44,3,FALSE),0)))
E10: =IF(B10="","",C10*IF(D10>0,D10,IFERROR(VLOOKUP(B10,Productos!$A$5:$C$44,3,FALSE),0)))
E11: =IF(B11="","",C11*IF(D11>0,D11,IFERROR(VLOOKUP(B11,Productos!$A$5:$C$44,3,FALSE),0)))
E12: =IF(B12="","",C12*IF(D12>0,D12,IFERROR(VLOOKUP(B12,Productos!$A$5:$C$44,3,FALSE),0)))
E13: =IF(B13="","",C13*IF(D13>0,D13,IFERROR(VLOOKUP(B13,Productos!$A$5:$C$44,3,FALSE),0)))
E14: =IF(B14="","",C14*IF(D14>0,D14,IFERROR(VLOOKUP(B14,Productos!$A$5:$C$44,3,FALSE),0)))
E15: =IF(B15="","",C15*IF(D15>0,D15,IFERROR(VLOOKUP(B15,Productos!$A$5:$C$44,3,FALSE),0)))
E16: =IF(B16="","",C16*IF(D16>0,D16,IFERROR(VLOOKUP(B16,Productos!$A$5:$C$44,3,FALSE),0)))
E17: =IF(B17="","",C17*IF(D17>0,D17,IFERROR(VLOOKUP(B17,Productos!$A$5:$C$44,3,FALSE),0)))
E18: =IF(B18="","",C18*IF(D18>0,D18,IFERROR(VLOOKUP(B18,Productos!$A$5:$C$44,3,FALSE),0)))
E19: =IF(B19="","",C19*IF(D19>0,D19,IFERROR(VLOOKUP(B19,Productos!$A$5:$C$44,3,FALSE),0)))
E20: =IF(B20="","",C20*IF(D20>0,D20,IFERROR(VLOOKUP(B20,Productos!$A$5:$C$44,3,FALSE),0)))
... E504: =IF(B504="","",C504*IF(D504>0,D504,IFERROR(VLOOKUP(B504,Productos!$A$5:$C$44,3,FALSE),0)))

Sheet Resumen
A1: Resumen del período
A2: Cuánto ganaste y cuánta plata tenés parada
A5: Ingresos por ventas | B5: =SUM(Ventas!E5:E504)
A6: Costo de la mercadería vendida | B6: =SUMPRODUCT(Productos!$B$5:$B$44,Productos!$I$5:$I$44)
A7: Comisiones y envíos (estimado con el precio de lista) | B7: =SUMPRODUCT(Productos!$C$5:$C$44,Productos!$D$5:$D$44,Productos!$I$5:$I$44)
A8: Ganancia bruta | B8: =B5-B6-B7
A9: Costos fijos del período | B9: =Parámetros!B4
A10: GANANCIA NETA | B10: =B8-B9
A11: Meta de ganancia | B11: =Parámetros!B5
A12: Falta para la meta (0 = cumplida) | B12: =MAX(0,B11-B10)
A13: Unidades vendidas | B13: =SUM(Productos!$I$5:$I$44)
A14: Plata invertida en mercadería comprada | B14: =SUMPRODUCT(Productos!$B$5:$B$44,Productos!$E$5:$E$44)
A15: Plata parada en stock (a costo) | B15: =SUMPRODUCT(Productos!$B$5:$B$44,Productos!$J$5:$J$44)
A16: Productos para reponer o sin stock | B16: =COUNTIF(Productos!$K$5:$K$44,"REPONER")+COUNTIF(Productos!$K$5:$K$44,"SIN STOCK")
A17: Producto más rentable | B17: =IFERROR(INDEX(Productos!$A$5:$A$44,MATCH(MAX(Productos!$L$5:$L$44),Productos!$L$5:$L$44,0)),"")
A19: Si la ganancia neta es negativa, los costos fijos todavía no se pagaron: revisá precios, comisiones y stock parado.
